[
  {
    "title": "About",
    "slug": "pages/about",
    "content": "const{Fragment:e,jsx:n,jsxs:t}=arguments[0];function _createMdxContent(i){const r={a:\"a\",h1:\"h1\",h2:\"h2\",li:\"li\",p:\"p\",ul:\"ul\",...i.components},{Callout:o}=r;return o||function(e,n){throw new Error(\"Expected \"+(n?\"component\":\"object\")+\" `\"+e+\"` to be defined: you likely forgot to import, pass, or provide it.\")}(\"Callout\",!0),t(e,{children:[n(r.h1,{id:\"about\",children:n(r.a,{className:\"anchor\",\"aria-label\":\"Link to section\",href:\"#about\",children:\"About\"})}),\"\\n\",n(r.p,{children:\"Senior Software Engineer. I build distributed systems, think hard about developer experience, and occasionally ship side projects that live here.\"}),\"\\n\",n(o,{type:\"info\",children:n(r.p,{children:\"Open to interesting conversations. Find me on GitHub or send an email — links in the footer.\"})}),\"\\n\",n(r.h2,{id:\"what-i-work-on\",children:n(r.a,{className:\"anchor\",\"aria-label\":\"Link to section\",href:\"#what-i-work-on\",children:\"What I work on\"})}),\"\\n\",t(r.ul,{children:[\"\\n\",n(r.li,{children:\"Distributed systems and reliability engineering\"}),\"\\n\",n(r.li,{children:\"Frontend performance and architecture\"}),\"\\n\",n(r.li,{children:\"Developer tooling and build systems\"}),\"\\n\",n(r.li,{children:\"Open source contributions\"}),\"\\n\"]}),\"\\n\",n(r.h2,{id:\"this-blog\",children:n(r.a,{className:\"anchor\",\"aria-label\":\"Link to section\",href:\"#this-blog\",children:\"This blog\"})}),\"\\n\",n(r.p,{children:\"Built with Next.js 15, MDX, Velite, and a lot of care. Fully static — no server, no database, no trackers.\"})]})}return{default:function(e={}){const{wrapper:t}=e.components||{};return t?n(t,{...e,children:n(_createMdxContent,{...e})}):_createMdxContent(e)}};"
  }
]